{
    "DUTION": "6",
    "WZS_ID": "79249",
    "EN_NAM": "Chen,Shei-Saint",
    "CH_NAM": "陳學聖",
    "METNAM": "立法院第8屆第6會期教育及文化委員會第21次全體委員會議",
    "ST_TIM": "2015-01-05 09:00",
    "SYS_ST": "11:00:27",
    "SYS_ET": "11:06:52",
    "COMTST": "教育及文化",
    "PHOTO_": "http:\/\/ivod.ly.gov.tw\/Image\/Pic\/photo_20150105110123_8722.jpg",
    "STAGE_": "8",
    "ENCNAM": "Education and Culture",
    "R": "3",
    "CLP_ST": "02:17:17",
    "FILNAM": "20150105110027_8722.mp4",
    "CM_NAM": "教育及文化委員會",
    "CLP_ET": "02:23:37",
    "METDEC": "邀請文化部部長、國防部部長等列席報告「文化部對現有文化資產及眷村文化保存成果及相關作為之執行情形」，並備質詢。(1月5日、1月7日、1月8日3天一次會)",
    "LFILEA": "Y",
    "MFILEA": "Y",
    "HFILEA": "N",
    "LFILEB": "Y",
    "MFILEB": "Y",
    "HFILEB": "N",
    "PUBLIC": "N",
    "LGLTIM": "11:00:27 - 11:06:52",
    "MOVTIM": "00:06:25"
}