{
    "DUTION": "3",
    "WZS_ID": "46232",
    "EN_NAM": "Hsu, Tain-Tsair",
    "CH_NAM": "許添財",
    "METNAM": "立法院第8屆第3會期財政委員會第12次全體委員會議",
    "ST_TIM": "2013-05-23 09:00",
    "SYS_ST": "09:19:00",
    "SYS_ET": "09:33:25",
    "COMTST": "財政",
    "PHOTO_": "http:\/\/ivod.ly.gov.tw\/Image\/Pic\/0523-093348-22-0.jpg",
    "STAGE_": "8",
    "ENCNAM": "Finance",
    "R": "343",
    "CLP_ST": "00:19:00",
    "FILNAM": "2013052309190046232.mp4",
    "CM_NAM": "財政委員會",
    "CLP_ET": "00:33:25",
    "METDEC": "上午邀請財政部張部長、金融監督管理委員會陳主任委員、經濟部張部長及相關單位首長列席報告十年來公股行庫5",
    "LFILEA": "Y",
    "MFILEA": "N",
    "HFILEA": "N",
    "LFILEB": "Y",
    "MFILEB": "N",
    "HFILEB": "N",
    "PUBLIC": "http:\/\/lci.ly.gov.tw\/LyLCEW\/lcivComm4VOD.action?Meeting_Date=1020523&p1_2=%E8%B2%A1%E6%94%BF&p4=%E8%A8%B1%E6%B7%BB%E8%B2%A1",
    "LGLTIM": "09:19:00 - 09:33:25",
    "MOVTIM": "00:14:25"
}