{
    "DUTION": "3",
    "WZS_ID": "9625",
    "EN_NAM": "Lee, Chun-Yi",
    "CH_NAM": "李俊俋",
    "METNAM": "立法院第8屆第3會期內政委員會第16次全體委員會議",
    "ST_TIM": "2013-04-15 09:00",
    "SYS_ST": "10:27:00",
    "SYS_ET": "10:41:05",
    "COMTST": "內政",
    "PHOTO_": "http:\/\/ivod.ly.gov.tw\/Image\/Pic\/0415-104125-19-0.jpg",
    "STAGE_": "8",
    "ENCNAM": "Internal Administration",
    "R": "112",
    "CLP_ST": "01:27:00",
    "FILNAM": "201304151027009625.mp4",
    "CM_NAM": "內政委員會",
    "CLP_ET": "01:41:05",
    "METDEC": "立法院第8屆第3會期內政委員會第16次全體委員會議：邀請行政院大陸委員會主任委員王郁琦、財團法人海峽交流基金會董事長林中森、內政部部長李鴻源就「歷次博鰲論壇之具體成效暨有關兩岸互設辦事處與中國白領員工來臺相關協議及法令研議情形」進行專題報告並備質詢；另請外交部、教育部、經濟部、行政院衛生署、行政院經濟建設委員會、金融監督管理委員會、行政院勞工委員會、國家安全局列席備詢。\n",
    "LFILEA": "Y",
    "MFILEA": "N",
    "HFILEA": "N",
    "LFILEB": "Y",
    "MFILEB": "N",
    "HFILEB": "N",
    "PUBLIC": "http:\/\/lci.ly.gov.tw\/LyLCEW\/lcivComm4VOD.action?Meeting_Date=1020415&p1_2=%E5%85%A7%E6%94%BF&p4=%E6%9D%8E%E4%BF%8A%E4%BF%8B",
    "LGLTIM": "10:27:00 - 10:41:05",
    "MOVTIM": "00:14:05"
}