{
    "DUTION": "5",
    "WZS_ID": "74182",
    "EN_NAM": "Wang, Yu-Min",
    "CH_NAM": "王育敏",
    "METNAM": null,
    "ST_TIM": "2014-04-21 09:00",
    "SYS_ST": "10:22:44",
    "SYS_ET": "10:35:11",
    "COMTST": "社會福利及衛生環境",
    "PHOTO_": "http:\/\/ivod.ly.gov.tw\/Image\/Pic\/photo_20140421102721_7523.jpg",
    "STAGE_": "8",
    "ENCNAM": "Social Welfare and Environmental Hygiene",
    "R": "64",
    "CLP_ST": "01:33:20",
    "FILNAM": "20140421102244_7523.mp4",
    "CM_NAM": "社會福利及衛生環境委員會",
    "CLP_ET": "01:45:45",
    "METDEC": "立法院第8屆第5會期社會福利及衛生環境委員會第15次全體委員會議一、邀請勞動部潘部長世偉、外交部次長、行政院大陸委員會副主任委員、交通部民用航空局副局長、經濟部、教育部、法務部等派員就「近5年來我國國人赴『海外工作』之概況(含類型、國別、人數、行業別及工作時間等統計資料)及其相關勞動權益保障問題」列席報告，並備質詢。\u000b二、審查本院委員潘孟安等18人擬具「就業保險法第二十二條條文修正草案」。\u000b三、併案審查本院委員楊麗環等18人擬具「家事勞工權益保障法草案」、委員林淑芬等24人擬具「家事服務法草案」等2案。",
    "LFILEA": "Y",
    "MFILEA": "Y",
    "HFILEA": "N",
    "LFILEB": "Y",
    "MFILEB": "Y",
    "HFILEB": "N",
    "PUBLIC": "http:\/\/lci.ly.gov.tw\/LyLCEW\/lcivComm4VOD.action?Meeting_Date=1030421&p1_2=%E7%A4%BE%E6%9C%83%E7%A6%8F%E5%88%A9%E5%8F%8A%E8%A1%9B%E7%94%9F%E7%92%B0%E5%A2%83&p4=%E7%8E%8B%E8%82%B2%E6%95%8F",
    "LGLTIM": "10:22:44 - 10:35:11",
    "MOVTIM": "00:12:27"
}