{
    "DUTION": "3",
    "WZS_ID": "16021",
    "EN_NAM": "Yang, Yao",
    "CH_NAM": "楊曜",
    "METNAM": "第8屆第3會期第7次會議",
    "ST_TIM": "2013-04-09 09:00",
    "SYS_ST": "15:41:00",
    "SYS_ET": "15:56:38",
    "COMTST": "院會",
    "PHOTO_": "http:\/\/ivod.ly.gov.tw\/Image\/Pic\/0409-155619-27-401.jpg",
    "STAGE_": "8",
    "ENCNAM": "Yuan Sitting",
    "R": "79",
    "CLP_ST": "06:41:00",
    "FILNAM": "2013040915410016021.mp4",
    "CM_NAM": "院會",
    "CLP_ET": "06:56:38",
    "METDEC": "一、上午9時至10時為國是論壇時間。二、對行政院院長提出施政方針及施政報告，繼續質詢。三、下午1時50分至2時30分為處理臨時提案時間。\n",
    "LFILEA": "Y",
    "MFILEA": "N",
    "HFILEA": "N",
    "LFILEB": "Y",
    "MFILEB": "N",
    "HFILEB": "N",
    "PUBLIC": "http:\/\/lci.ly.gov.tw\/LyLCEW\/lcivComm4VOD.action?Meeting_Date=1020409&p1_2=%E9%99%A2%E6%9C%83&p4=%E6%A5%8A%E6%9B%9C",
    "LGLTIM": "15:41:00 - 15:56:38",
    "MOVTIM": "00:15:38"
}