{
    "DUTION": "6",
    "WZS_ID": "78546",
    "EN_NAM": "Wang, Yu-Min",
    "CH_NAM": "王育敏",
    "METNAM": "第8屆第6會期程序委員會第12次會議審定本院第8屆第6會期第12次會議議事",
    "ST_TIM": "2014-12-02 12:00",
    "SYS_ST": "12:11:31",
    "SYS_ET": "12:12:00",
    "COMTST": "程序",
    "PHOTO_": "http:\/\/ivod.ly.gov.tw\/Image\/Pic\/photo_20141202121150_8540.jpg",
    "STAGE_": "8",
    "ENCNAM": "Procedure",
    "R": "2",
    "CLP_ST": "00:22:00",
    "FILNAM": "20141202121131_8540.mp4",
    "CM_NAM": "程序委員會",
    "CLP_ET": "00:22:28",
    "METDEC": "審定本院第8屆第6會期第12次會議議事",
    "LFILEA": "Y",
    "MFILEA": "Y",
    "HFILEA": "N",
    "LFILEB": "Y",
    "MFILEB": "Y",
    "HFILEB": "N",
    "PUBLIC": "N",
    "LGLTIM": "12:11:31 - 12:12:00",
    "MOVTIM": "00:00:29"
}