{
    "DUTION": "5",
    "WZS_ID": "74816",
    "EN_NAM": "Yang, Yao",
    "CH_NAM": "楊曜",
    "METNAM": null,
    "ST_TIM": "2014-05-06 09:00",
    "SYS_ST": "17:37:44",
    "SYS_ET": "17:53:39",
    "COMTST": "院會",
    "PHOTO_": "http:\/\/ivod.ly.gov.tw\/Image\/Pic\/photo_20140506173814_7580.jpg",
    "STAGE_": "8",
    "ENCNAM": "Yuan Sitting",
    "R": "25",
    "CLP_ST": "03:02:10",
    "FILNAM": "20140506173744_7580.mp4",
    "CM_NAM": "院會",
    "CLP_ET": "03:18:05",
    "METDEC": "第8屆第5會期第8次會議一、2日上午9時至10時為國是論壇時間。二、對行政院院長提出施政方針及施政報告，繼續質詢。三、6日下午1時50分至2時30分為處理臨時提案時間。",
    "LFILEA": "Y",
    "MFILEA": "Y",
    "HFILEA": "N",
    "LFILEB": "Y",
    "MFILEB": "Y",
    "HFILEB": "N",
    "PUBLIC": "http:\/\/lci.ly.gov.tw\/LyLCEW\/lcivComm4VOD.action?Meeting_Date=1030506&p1_2=%E9%99%A2%E6%9C%83&p4=%E6%A5%8A%E6%9B%9C",
    "LGLTIM": "17:37:44 - 17:53:39",
    "MOVTIM": "00:15:55"
}