{
    "DUTION": "5",
    "WZS_ID": "74675",
    "EN_NAM": "Tseng, Chu-Wei",
    "CH_NAM": "曾巨威",
    "METNAM": null,
    "ST_TIM": "2014-05-02 09:00",
    "SYS_ST": "18:38:54",
    "SYS_ET": "19:10:49",
    "COMTST": "院會",
    "PHOTO_": "http:\/\/ivod.ly.gov.tw\/Image\/Pic\/photo_20140502183942_7579.jpg",
    "STAGE_": "8",
    "ENCNAM": "Yuan Sitting",
    "R": "32",
    "CLP_ST": "09:54:47",
    "FILNAM": "20140502183854_7579.mp4",
    "CM_NAM": "院會",
    "CLP_ET": "10:26:42",
    "METDEC": "第8屆第5會期第8次會議一、2日上午9時至10時為國是論壇時間。二、對行政院院長提出施政方針及施政報告，繼續質詢。三、6日下午1時50分至2時30分為處理臨時提案時間。",
    "LFILEA": "Y",
    "MFILEA": "Y",
    "HFILEA": "N",
    "LFILEB": "Y",
    "MFILEB": "Y",
    "HFILEB": "N",
    "PUBLIC": "http:\/\/lci.ly.gov.tw\/LyLCEW\/lcivComm4VOD.action?Meeting_Date=1030502&p1_2=%E9%99%A2%E6%9C%83&p4=%E6%9B%BE%E5%B7%A8%E5%A8%81",
    "LGLTIM": "18:38:54 - 19:10:49",
    "MOVTIM": "00:31:55"
}