{
    "DUTION": "4",
    "WZS_ID": "69839",
    "EN_NAM": "Lu, Yu-Ling",
    "CH_NAM": "呂玉玲",
    "METNAM": null,
    "ST_TIM": "2013-11-05 09:00",
    "SYS_ST": "09:54:00",
    "SYS_ET": "10:09:08",
    "COMTST": "院會",
    "PHOTO_": "http:\/\/ivod.ly.gov.tw\/Image\/Pic\/1105-100844-27-378.jpg",
    "STAGE_": "8",
    "ENCNAM": "Yuan Sitting",
    "R": "48",
    "CLP_ST": null,
    "FILNAM": "2013-11-05_09-54-00_2516_19.mp4",
    "CM_NAM": "院會",
    "CLP_ET": null,
    "METDEC": "第8屆第4會期第8次會議一、1日上午9時至10時為國是論壇時間。二、對行政院院長施政報告，繼續質詢。三、5日下午1時50分至2時30分為處理臨時提案時間。四、討論事項：行政院函請審議「海關進口稅則部分稅則修正草案」案。（5日對行政院院長施政報告質詢後，隨即處理）",
    "LFILEA": "Y",
    "MFILEA": "N",
    "HFILEA": "N",
    "LFILEB": "Y",
    "MFILEB": "N",
    "HFILEB": "N",
    "PUBLIC": "http:\/\/lci.ly.gov.tw\/LyLCEW\/lcivComm4VOD.action?Meeting_Date=1021105&p1_2=%E9%99%A2%E6%9C%83&p4=%E5%91%82%E7%8E%89%E7%8E%B2",
    "LGLTIM": "09:54:00 - 10:09:08",
    "MOVTIM": "00:15:08"
}