{
    "DUTION": "4",
    "WZS_ID": "67689",
    "EN_NAM": "Liao, Cheng-Ching",
    "CH_NAM": "廖正井",
    "METNAM": null,
    "ST_TIM": "2013-12-16 14:30",
    "SYS_ST": "15:06:57",
    "SYS_ET": "15:09:57",
    "COMTST": "交通",
    "PHOTO_": "http:\/\/ivod.ly.gov.tw\/Image\/Pic\/photo_20131216150711.jpg",
    "STAGE_": "8",
    "ENCNAM": "Transportation",
    "R": "78",
    "CLP_ST": "00:13:03",
    "FILNAM": "20131216150657_6924.mp4",
    "CM_NAM": "交通委員會",
    "CLP_ET": "00:15:53",
    "METDEC": "立法院第8屆第4會期交通、內政委員會第2次聯席會議審查委員廖正井等39人擬具「國際機場園區發展條例第十四條條文修正草案」案。",
    "LFILEA": "Y",
    "MFILEA": "Y",
    "HFILEA": "Y",
    "LFILEB": "Y",
    "MFILEB": "Y",
    "HFILEB": "Y",
    "PUBLIC": "http:\/\/lci.ly.gov.tw\/LyLCEW\/lcivComm4VOD.action?Meeting_Date=1021216&p1_2=%E4%BA%A4%E9%80%9A&p4=%E5%BB%96%E6%AD%A3%E4%BA%95",
    "LGLTIM": "15:06:57 - 15:09:57",
    "MOVTIM": "00:03:00"
}