{
    "DUTION": "4",
    "WZS_ID": "71732",
    "EN_NAM": "Chang, Chia-Chun",
    "CH_NAM": "張嘉郡",
    "METNAM": null,
    "ST_TIM": "2013-12-25 09:00",
    "SYS_ST": "10:45:00",
    "SYS_ET": "10:52:54",
    "COMTST": "經濟",
    "PHOTO_": "http:\/\/ivod.ly.gov.tw\/Image\/Pic\/1225-105303-21-0.jpg",
    "STAGE_": "8",
    "ENCNAM": "Economics",
    "R": "12",
    "CLP_ST": null,
    "FILNAM": "2013-12-25_10-45-00_2509_5.mp4",
    "CM_NAM": "經濟委員會",
    "CLP_ET": null,
    "METDEC": "立法院第8屆第4會期經濟委員會第16次全體委員會議一、併案審查本院委員李貴敏等26人擬具「專利法增訂部分條文草案」案、委員黃偉哲等16人擬具「專利法第一百四十三條條文修正草案」案。（詢答及處理）二、併案審查本院委員王惠美等20人擬具「工廠管理輔導法第三十三條及第三十四條條文修正草案」案、委員林岱樺等23人擬具「工廠管理輔導法第三十三條及第三十四條條文修正草案」案、委員何欣純等17人擬具「工廠管理輔導法第三十三條及第三十四條條文修正草案」案、委員顏寬恒等21人擬具「工廠管理輔導法第三十三條條文修正草案」案。（處理）（12月23日下午、25日二天一次會)",
    "LFILEA": "Y",
    "MFILEA": "N",
    "HFILEA": "N",
    "LFILEB": "Y",
    "MFILEB": "N",
    "HFILEB": "N",
    "PUBLIC": "http:\/\/lci.ly.gov.tw\/LyLCEW\/lcivComm4VOD.action?Meeting_Date=1021225&p1_2=%E7%B6%93%E6%BF%9F&p4=%E5%BC%B5%E5%98%89%E9%83%A1",
    "LGLTIM": "10:45:00 - 10:52:54",
    "MOVTIM": "00:07:54"
}