{
    "DUTION": "6",
    "WZS_ID": "76790",
    "EN_NAM": "Chen,Yi-Jie",
    "CH_NAM": "陳怡潔",
    "METNAM": "第8屆第6會期第4次會議",
    "ST_TIM": "2014-10-03 09:00",
    "SYS_ST": "15:18:17",
    "SYS_ET": "15:49:22",
    "COMTST": "院會",
    "PHOTO_": "http:\/\/ivod.ly.gov.tw\/Image\/Pic\/photo_20141003151842_8116.jpg",
    "STAGE_": "8",
    "ENCNAM": "Yuan Sitting",
    "R": "14",
    "CLP_ST": "06:47:33",
    "FILNAM": "20141003151817_8116.mp4",
    "CM_NAM": "院會",
    "CLP_ET": "07:18:38",
    "METDEC": "一、3日上午9時至10時為國是論壇時間。二、對行政院院長施政報告繼續質詢。三、7日下午1時50分至2時30分為臨時提案時間。",
    "LFILEA": "Y",
    "MFILEA": "Y",
    "HFILEA": "N",
    "LFILEB": "Y",
    "MFILEB": "Y",
    "HFILEB": "N",
    "PUBLIC": "http:\/\/lci.ly.gov.tw\/LyLCEW\/lcivComm4VOD.action?Meeting_Date=1031003&p1_2=%E9%99%A2%E6%9C%83&p4=%E9%99%B3%E6%80%A1%E6%BD%94",
    "LGLTIM": "15:18:17 - 15:49:22",
    "MOVTIM": "00:31:05"
}