{
    "DUTION": "6",
    "WZS_ID": "77473",
    "EN_NAM": "Lai, Zhen-Chang",
    "CH_NAM": "賴振昌",
    "METNAM": "立法院第8屆第6會期財政委員會第7次全體委員會議",
    "ST_TIM": "2014-10-20 09:00",
    "SYS_ST": "11:12:48",
    "SYS_ET": "11:23:36",
    "COMTST": "財政",
    "PHOTO_": "http:\/\/ivod.ly.gov.tw\/Image\/Pic\/photo_20141020111326_8353.jpg",
    "STAGE_": "8",
    "ENCNAM": "Finance",
    "R": "26",
    "CLP_ST": "02:09:40",
    "FILNAM": "20141020111248_8353.mp4",
    "CM_NAM": "財政委員會",
    "CLP_ET": "02:20:27",
    "METDEC": "審查中華民國104年度中央政府總預算案有關賦稅署、臺北國稅局、高雄國稅局、北區國稅局及所屬、中區國稅局及所屬、南區國稅局及所屬歲出預算部分。",
    "LFILEA": "Y",
    "MFILEA": "Y",
    "HFILEA": "N",
    "LFILEB": "Y",
    "MFILEB": "Y",
    "HFILEB": "N",
    "PUBLIC": "http:\/\/lci.ly.gov.tw\/LyLCEW\/lcivComm4VOD.action?Meeting_Date=1031020&p1_2=%E8%B2%A1%E6%94%BF&p4=%E8%B3%B4%E6%8C%AF%E6%98%8C",
    "LGLTIM": "11:12:48 - 11:23:36",
    "MOVTIM": "00:10:48"
}