{
    "DUTION": "6",
    "WZS_ID": "77600",
    "EN_NAM": "Zhou, Ni-An",
    "CH_NAM": "周倪安",
    "METNAM": "立法院第8屆第6會期內政委員會第13次全體委員會議",
    "ST_TIM": "2014-10-22 09:00",
    "SYS_ST": "09:55:26",
    "SYS_ET": "10:08:36",
    "COMTST": "內政",
    "PHOTO_": "http:\/\/ivod.ly.gov.tw\/Image\/Pic\/photo_20141022095706_8370.jpg",
    "STAGE_": "8",
    "ENCNAM": "Internal Administration",
    "R": "34",
    "CLP_ST": "01:04:37",
    "FILNAM": "20141022095526_8370.mp4",
    "CM_NAM": "內政委員會",
    "CLP_ET": "01:17:44",
    "METDEC": "一、審查104年度中央政府總預算案關於中央選舉委員會及所屬收支部分。\u000b二、審查中央選舉委員會及所屬近3年「辦理政策宣導相關廣告執行情形」共5案。",
    "LFILEA": "Y",
    "MFILEA": "Y",
    "HFILEA": "N",
    "LFILEB": "Y",
    "MFILEB": "Y",
    "HFILEB": "N",
    "PUBLIC": "http:\/\/lci.ly.gov.tw\/LyLCEW\/lcivComm4VOD.action?Meeting_Date=1031022&p1_2=%E5%85%A7%E6%94%BF&p4=%E5%91%A8%E5%80%AA%E5%AE%89",
    "LGLTIM": "09:55:26 - 10:08:36",
    "MOVTIM": "00:13:10"
}