{
    "DUTION": "3",
    "WZS_ID": "10371",
    "EN_NAM": "Lin, Hung-Chih",
    "CH_NAM": "林鴻池",
    "METNAM": "第8屆第3會期第16次會議一、審定本院第8屆第3會期第1次臨時會第1次會議",
    "ST_TIM": "2013-06-13 12:00",
    "SYS_ST": "12:22:00",
    "SYS_ET": "12:23:31",
    "COMTST": "程序",
    "PHOTO_": "http:\/\/ivod.ly.gov.tw\/Image\/Pic\/0613-122308-28-266.jpg",
    "STAGE_": "8",
    "ENCNAM": "Procedure",
    "R": "47",
    "CLP_ST": "00:22:00",
    "FILNAM": "2013061312220010371.mp4",
    "CM_NAM": "程序委員會",
    "CLP_ET": "00:23:31",
    "METDEC": "第8屆第3會期第16次會議一、審定本院第8屆第3會期第1次臨時會第1次會議議事日程\n\n\n\n二、審定本院第8屆第3會期第1次臨時會第1次全院委員會會議議事日程\n\n\n\n\n",
    "LFILEA": "Y",
    "MFILEA": "N",
    "HFILEA": "N",
    "LFILEB": "Y",
    "MFILEB": "N",
    "HFILEB": "N",
    "PUBLIC": "http:\/\/lci.ly.gov.tw\/LyLCEW\/lcivComm4VOD.action?Meeting_Date=1020613&p1_2=%E7%A8%8B%E5%BA%8F&p4=%E6%9E%97%E9%B4%BB%E6%B1%A0",
    "LGLTIM": "12:22:00 - 12:23:31",
    "MOVTIM": "00:01:31"
}