{
    "DUTION": "5",
    "WZS_ID": "75025",
    "EN_NAM": "Lee, Kun-Tse",
    "CH_NAM": "李昆澤",
    "METNAM": null,
    "ST_TIM": "2014-05-12 09:00",
    "SYS_ST": "09:28:35",
    "SYS_ET": "09:42:26",
    "COMTST": "交通",
    "PHOTO_": "http:\/\/ivod.ly.gov.tw\/Image\/Pic\/photo_20140512093421_7626.jpg",
    "STAGE_": "8",
    "ENCNAM": "Transportation",
    "R": "36",
    "CLP_ST": "00:38:16",
    "FILNAM": "20140512092835_7626.mp4",
    "CM_NAM": "交通委員會",
    "CLP_ET": "00:52:06",
    "METDEC": "立法院第8屆第5會期交通委員會第11次全體委員會議邀請交通部部長葉匡時率同所屬列席就「臺鐵及高鐵行車安全之管理、事故分析以及改善預防措施」提出報告，並備質詢；並請台灣高速鐵路股份有限公司董事長范志強列席備詢。(5月12日及5月15日二天一次會)",
    "LFILEA": "Y",
    "MFILEA": "Y",
    "HFILEA": "N",
    "LFILEB": "Y",
    "MFILEB": "Y",
    "HFILEB": "N",
    "PUBLIC": "http:\/\/lci.ly.gov.tw\/LyLCEW\/lcivComm4VOD.action?Meeting_Date=1030512&p1_2=%E4%BA%A4%E9%80%9A&p4=%E6%9D%8E%E6%98%86%E6%BE%A4",
    "LGLTIM": "09:28:35 - 09:42:26",
    "MOVTIM": "00:13:51"
}