{
    "DUTION": "3",
    "WZS_ID": "46141",
    "EN_NAM": "Wei, Ming-Ku",
    "CH_NAM": "魏明谷",
    "METNAM": "立法院第8屆第3會期交通委員會第11次全體委員會議",
    "ST_TIM": "2013-05-15 09:00",
    "SYS_ST": "10:47:00",
    "SYS_ET": "10:59:50",
    "COMTST": "交通",
    "PHOTO_": "http:\/\/ivod.ly.gov.tw\/Image\/Pic\/0515-105936-24-0.jpg",
    "STAGE_": "8",
    "ENCNAM": "Transportation",
    "R": "44",
    "CLP_ST": "01:47:00",
    "FILNAM": "2013051510470046141.mp4",
    "CM_NAM": "交通委員會",
    "CLP_ET": "01:59:50",
    "METDEC": "立法院第8屆第3會期交通委員會第11次全體委員會議上午：一、邀請交通部部長葉匡時率同所屬列席報告航港局及臺灣港務股份有限公司業務概況，並備質詢。二、審查委員李昆澤等25人擬具「商港法第十一條條文修正草案」案。三、審查行政院函請審議「航業法部分條文修正草案」案。（本案如經復議，則不予審查）(5月13、15日及16日三天一次會)\n",
    "LFILEA": "Y",
    "MFILEA": "N",
    "HFILEA": "N",
    "LFILEB": "Y",
    "MFILEB": "N",
    "HFILEB": "N",
    "PUBLIC": "http:\/\/lci.ly.gov.tw\/LyLCEW\/lcivComm4VOD.action?Meeting_Date=1020515&p1_2=%E4%BA%A4%E9%80%9A&p4=%E9%AD%8F%E6%98%8E%E8%B0%B7",
    "LGLTIM": "10:47:00 - 10:59:50",
    "MOVTIM": "00:12:50"
}