{
    "DUTION": "5",
    "WZS_ID": "73596",
    "EN_NAM": "Wu, Yu-Jen",
    "CH_NAM": "吳育仁",
    "METNAM": null,
    "ST_TIM": "2014-04-03 09:00",
    "SYS_ST": "09:22:49",
    "SYS_ET": "09:33:10",
    "COMTST": "社會福利及衛生環境",
    "PHOTO_": "http:\/\/ivod.ly.gov.tw\/Image\/Pic\/photo_20140403093058_7418.jpg",
    "STAGE_": "8",
    "ENCNAM": "Social Welfare and Environmental Hygiene",
    "R": "55",
    "CLP_ST": "00:34:37",
    "FILNAM": "20140403092249_7418.mp4",
    "CM_NAM": "社會福利及衛生環境委員會",
    "CLP_ET": "00:44:58",
    "METDEC": "立法院第8屆第5會期社會福利及衛生環境委員會第10次全體委員會議併案審查行政院函請審議「資源循環利用法草案」、本院委員林淑芬等22人擬具「廢棄物減量及循環利用法草案」、委員江惠貞等40人擬具「廢棄資源循環利用法草案」等3案。",
    "LFILEA": "Y",
    "MFILEA": "Y",
    "HFILEA": "N",
    "LFILEB": "Y",
    "MFILEB": "Y",
    "HFILEB": "N",
    "PUBLIC": "http:\/\/lci.ly.gov.tw\/LyLCEW\/lcivComm4VOD.action?Meeting_Date=1030403&p1_2=%E7%A4%BE%E6%9C%83%E7%A6%8F%E5%88%A9%E5%8F%8A%E8%A1%9B%E7%94%9F%E7%92%B0%E5%A2%83&p4=%E5%90%B3%E8%82%B2%E4%BB%81",
    "LGLTIM": "09:22:49 - 09:33:10",
    "MOVTIM": "00:10:21"
}