{
    "DUTION": "3",
    "WZS_ID": "35282",
    "EN_NAM": "Hsu, Chih-Chieh",
    "CH_NAM": "許智傑",
    "METNAM": "立法院第8屆第3會期第1次臨時會教育及文化委員會第1次全體委員會議",
    "ST_TIM": "2013-06-20 09:00",
    "SYS_ST": "09:55:00",
    "SYS_ET": "10:01:59",
    "COMTST": "教育及文化",
    "PHOTO_": "http:\/\/ivod.ly.gov.tw\/Image\/Pic\/0620-100156-23-0.jpg",
    "STAGE_": "8",
    "ENCNAM": "Education and Culture",
    "R": "71",
    "CLP_ST": "00:55:00",
    "FILNAM": "2013062009550035282.mp4",
    "CM_NAM": "教育及文化委員會",
    "CLP_ET": "01:01:59",
    "METDEC": "立法院第8屆第3會期第1次臨時會教育及文化委員會第1次全體委員會議審查行政院函請審議「教師法第十四條條文修正草案」案。\n",
    "LFILEA": "Y",
    "MFILEA": "N",
    "HFILEA": "N",
    "LFILEB": "Y",
    "MFILEB": "N",
    "HFILEB": "N",
    "PUBLIC": "http:\/\/lci.ly.gov.tw\/LyLCEW\/lcivComm4VOD.action?Meeting_Date=1020620&p1_2=%E6%95%99%E8%82%B2%E5%8F%8A%E6%96%87%E5%8C%96&p4=%E8%A8%B1%E6%99%BA%E5%82%91",
    "LGLTIM": "09:55:00 - 10:01:59",
    "MOVTIM": "00:06:59"
}